files_to_prompt/__init__.py
files_to_prompt/__main__.py
files_to_prompt/cli.py
files_to_prompt_ext-0.6.4.3.dist-info/licenses/LICENSE
files_to_prompt_ext-0.6.4.3.dist-info/METADATA
files_to_prompt_ext-0.6.4.3.dist-info/WHEEL
files_to_prompt_ext-0.6.4.3.dist-info/entry_points.txt
files_to_prompt_ext-0.6.4.3.dist-info/top_level.txt
files_to_prompt_ext-0.6.4.3.dist-info/RECORD
