Metadata-Version: 2.4
Name: files-to-prompt-ext
Version: 0.6.4.3
Summary: Build project file/directory context prompts for use with LLMs
Author: Janis Hahn
License: Apache-2.0
Project-URL: Homepage, https://github.com/janishahn/files-to-prompt
Classifier: License :: OSI Approved :: Apache Software License
Requires-Python: >=3.8
License-File: LICENSE
Requires-Dist: click
Requires-Dist: tiktoken
Provides-Extra: test
Requires-Dist: pytest; extra == "test"
Dynamic: license-file
